nist_asd-1.4.dist-info/METADATA
nist_asd-1.4.dist-info/RECORD
nist_asd-1.4.dist-info/WHEEL
nist_asd-1.4.dist-info/top_level.txt
nistasd/__init__.py
nistasd/nist_asd_parser.py
